age_cda/Check.py
age_cda/Exception.py
age_cda/Graph.py
age_cda/Lib.py
age_cda/VERSION.py
age_cda/__init__.py
age_cda/lib_ubuntu/library.so
age_cda/lib_windows/x64/Release/gsl.dll
age_cda/lib_windows/x64/Release/gslcblas.dll
age_cda/lib_windows/x64/Release/lib_windows.dll
age_cda/lib_windows/x86/Release/gsl.dll
age_cda/lib_windows/x86/Release/gslcblas.dll
age_cda/lib_windows/x86/Release/lib_windows.dll
age_cda-0.0.4.dist-info/LICENSE
age_cda-0.0.4.dist-info/METADATA
age_cda-0.0.4.dist-info/WHEEL
age_cda-0.0.4.dist-info/top_level.txt
age_cda-0.0.4.dist-info/RECORD
