Metadata-Version: 2.1
Name: age-cda
Version: 0.0.4
Summary: Detection of Community by maximizing modularity
Home-page: https://github.com/Munmud/Community-Detection-Modularity
Author: Moontasir Mahmood
Author-email: moontasir042@gmail.com
License: Apache2.0
Keywords: Community-Detection,Modularity,Reichardt and Bornholdt,Newman,partition network,k means cluster
Classifier: Programming Language :: Python :: 3.9
Requires-Python: >=3.9
License-File: LICENSE
